klsudoku.cp37-win_amd64.pyd
klsudoku-1.0.dist-info/METADATA
klsudoku-1.0.dist-info/WHEEL
klsudoku-1.0.dist-info/top_level.txt
klsudoku-1.0.dist-info/RECORD
