Metadata-Version: 2.1
Name: klsudoku
Version: 1.0
Summary: Sudoku solver package.
Home-page: https://github.com/ttylikl/klsudoku/
Author: ttylikl
Author-email: ttylikl@gmail.com
License: UNKNOWN
Platform: UNKNOWN
